{
    "id": "113",
    "name": "Bouncer",
    "author": "🇺🇸 notcoolboy1",
    "creators": ["🇺🇸 notcoolboy1, 🇺🇸 SME"],
    "verifier": "🇺🇸 notcoolboy1",
    "verification": "https://youtu.be/SgPGmLvL_TE",
    "percentToQualify": "48",
    "password": "Free to Copy",
    "records": [
         {
            "user": "🇺🇸 SME",
            "link": "https://youtu.be/R9XaldnB1RA",
            "percent": "100",
            "date": "10/29/2025"
        },
       {
            "user": "🇮🇹 Scatter",
            "link": "https://youtu.be/g3SWgzj5YKA",
            "percent": "100",
            "date": "10/30/2025"
        },
        {
            "user": "🇮🇹 Ali",
            "link": "https://youtu.be/4aVgNRPGoog",
            "percent": "100",
            "date": "11/6/2025"
        }
    ]
}